[{"name": "AtCoder Grand Contest 069", "contest_url": "https://atcoder.jp/contests/agc069", "start_time": 1732478400.0, "durationSeconds": 10800, "end_time": 1732489200.0, "platform": "AtCoder"},{"name": "HACK TO THE FUTURE 2025  (AtCoder Heuristic Contest 040)", "contest_url": "https://atcoder.jp/contests/ahc040", "start_time": 1732903200.0, "durationSeconds": 864000, "end_time": 1733767200.0, "platform": "AtCoder"},{"name": "AtCoder Beginner Contest 382", "contest_url": "https://atcoder.jp/contests/abc382", "start_time": 1732996800.0, "durationSeconds": 6000, "end_time": 1733002800.0, "platform": "AtCoder"},{"name": "Daiwa Securities Co. Ltd. Programming Contest 2024（AtCoder Beginner Contest 383）", "contest_url": "https://atcoder.jp/contests/abc383", "start_time": 1733601600.0, "durationSeconds": 6000, "end_time": 1733607600.0, "platform": "AtCoder"},{"name": "Toyota Programming Contest 2024#12（AtCoder Beginner Contest 384）", "contest_url": "https://atcoder.jp/contests/abc384", "start_time": 1734206400.0, "durationSeconds": 6000, "end_time": 1734212400.0, "platform": "AtCoder"},{"name": "AtCoder Beginner Contest 386", "contest_url": "https://atcoder.jp/contests/abc386", "start_time": 1735416000.0, "durationSeconds": 6000, "end_time": 1735422000.0, "platform": "AtCoder"},{"name": "AtCoder Grand Contest 070", "contest_url": "https://atcoder.jp/contests/agc070", "start_time": 1735502400.0, "durationSeconds": 10800, "end_time": 1735513200.0, "platform": "AtCoder"},{"name": "AtCoder Beginner Contest 387", "contest_url": "https://atcoder.jp/contests/abc387", "start_time": 1736020800.0, "durationSeconds": 6000, "end_time": 1736026800.0, "platform": "AtCoder"},{"name": "The 2nd Masters Championship-qual-", "contest_url": "https://atcoder.jp/contests/masters2025-qual", "start_time": 1740916800.0, "durationSeconds": 21600, "end_time": 1740938400.0, "platform": "AtCoder"}]