[{"name": "AtCoder Regular Contest 118", "contest_url": "https://atcoder.jp/contests/arc118", "start_time": 1620590400.0, "durationSeconds": 7200, "end_time": 1620597600.0, "platform": "AtCoder"},{"name": "Mynavi Programming Contest 2021（AtCoder Beginner Contest 201）", "contest_url": "https://atcoder.jp/contests/abc201", "start_time": 1621108800.0, "durationSeconds": 6000, "end_time": 1621114800.0, "platform": "AtCoder"},{"name": "AtCoder Regular Contest 119", "contest_url": "https://atcoder.jp/contests/arc119", "start_time": 1621195200.0, "durationSeconds": 7200, "end_time": 1621202400.0, "platform": "AtCoder"},{"name": "AtCoder Heuristic Contest 003", "contest_url": "https://atcoder.jp/contests/ahc003", "start_time": 1621681200.0, "durationSeconds": 720000, "end_time": 1622401200.0, "platform": "AtCoder"},{"name": "AtCoder Regular Contest 120", "contest_url": "https://atcoder.jp/contests/arc120", "start_time": 1621800000.0, "durationSeconds": 7200, "end_time": 1621807200.0, "platform": "AtCoder"}]