[{"isSignUp": false, "teamName": "", "contestDuration": 14400000, "contestEndTime": 1684573200000, "contestStartTime": 1684558800000, "topCategoryId": 14, "creatorId": 540562653, "creatorName": "世界第一可爱的嘤嘤嘤", "signUpEndCountDownTime": -401959407, "contestName": "福建农林大学校赛（同步赛）", "type": 0, "settingInfo": {"allowTeamSignUp": false, "isProblemAutoOpen": false, "needSignUpField": false, "rankFrozenMillisecond": 3600000, "excitationStatus": "Finished", "problemOriginal": true, "needRankFrozen": true, "rankFrozenMinute": 60, "logoUrl": "https://uploadfiles.nowcoder.com/images/20230519/540562653_1684430394210/83750F556FE3FC9DEAC19BD3B1F432FE", "needSignUpRedirect": false, "forceOnlyMyStatusFilter": true, "needUserNameFormat": false, "organizerSchool": "福建农林大学", "sameEndTimeAsSignUpEnd": true, "managerList": [529320224], "needPassword": false, "organizerName": "福建农林大学", "needCharge": false, "allowMessage": true, "ratingStatus": "No", "needRatingUpperLimit": false, "rankSaveStatus": "Finished"}, "countDownTime": -416359407, "signUpCount": 245, "contestId": 58568, "contestSignUpEndTime": 1684573200000, "userLevel": 5, "teamId": 0, "isManager": false, "isTeamSignUp": false, "contestSignUpStartTime": 1684430398000, "signUpCountDownTime": -544761407, "filledPassword": false, "start_time": 1684558800, "end_time": 1684573200, "durationSeconds": 14400, "name": "福建农林大学校赛（同步赛）", "platform": "牛客", "contest_url": "https://ac.nowcoder.com/acm/contest/58568"},{"isSignUp": false, "teamName": "", "contestDuration": 14400000, "contestEndTime": 1684056600000, "contestStartTime": 1684042200000, "topCategoryId": 14, "creatorId": 826424238, "creatorName": "椎名真白_Mashiro", "signUpEndCountDownTime": -918559409, "contestName": "第二十届宁波大学程序设计竞赛（同步赛）", "type": 0, "settingInfo": {"allowTeamSignUp": true, "isProblemAutoOpen": false, "needSignUpField": false, "problemOriginal": true, "needRankFrozen": false, "logoUrl": "https://uploadfiles.nowcoder.com/images/20230408/826424238_1680886300917/8E106B637BCE706C8C8E69FFCA9233D5", "needSignUpRedirect": false, "forceOnlyMyStatusFilter": false, "needUserNameFormat": false, "organizerSchool": "宁波大学", "sameEndTimeAsSignUpEnd": true, "managerList": [], "needPassword": false, "organizerName": "宁波大学", "needCharge": false, "allowMessage": true, "ratingStatus": "No", "needRatingUpperLimit": false, "rankSaveStatus": "Finished"}, "countDownTime": -932959409, "signUpCount": 776, "contestId": 55515, "contestSignUpEndTime": 1684056600000, "userLevel": 3, "teamId": 0, "isManager": false, "isTeamSignUp": false, "contestSignUpStartTime": 1683513914000, "signUpCountDownTime": -1461245409, "filledPassword": false, "start_time": 1684042200, "end_time": 1684056600, "durationSeconds": 14400, "name": "第二十届宁波大学程序设计竞赛（同步赛）", "platform": "牛客", "contest_url": "https://ac.nowcoder.com/acm/contest/55515"},{"isSignUp": false, "teamName": "", "contestDuration": 18000000, "contestEndTime": 1683453600000, "contestStartTime": 1683435600000, "topCategoryId": 14, "creatorId": 714737194, "creatorName": "哭晕了", "signUpEndCountDownTime": -1521559410, "contestName": "第17届福建工程学院校赛（同步赛）", "type": 0, "settingInfo": {"allowTeamSignUp": false, "isProblemAutoOpen": false, "needSignUpField": false, "excitationStatus": "Finished", "problemOriginal": true, "needRankFrozen": false, "logoUrl": "https://uploadfiles.nowcoder.com/images/20230427/714737194_1682571198355/68D6ED7F5F979505D83347075459B27C", "needSignUpRedirect": false, "forceOnlyMyStatusFilter": false, "needUserNameFormat": false, "organizerSchool": "福建工程学院", "sameEndTimeAsSignUpEnd": false, "managerList": [], "needPassword": false, "organizerName": "nowcoder", "needCharge": false, "allowMessage": false, "ratingStatus": "No", "needRatingUpperLimit": false, "rankSaveStatus": "Finished"}, "countDownTime": -1539559410, "signUpCount": 227, "contestId": 56866, "contestSignUpEndTime": 1683453600000, "userLevel": 4, "teamId": 0, "isManager": false, "isTeamSignUp": false, "contestSignUpStartTime": 1682571600000, "signUpCountDownTime": -2403559410, "filledPassword": false, "start_time": 1683435600, "end_time": 1683453600, "durationSeconds": 18000, "name": "第17届福建工程学院校赛（同步赛）", "platform": "牛客", "contest_url": "https://ac.nowcoder.com/acm/contest/56866"},{"isSignUp": false, "teamName": "", "contestDuration": 18000000, "contestEndTime": 1683453600000, "contestStartTime": 1683435600000, "topCategoryId": 14, "creatorId": 276967795, "creatorName": "凡叽咯", "signUpEndCountDownTime": -1521559412, "contestName": "第十九届西南科技大学ACM程序设计竞赛（同步赛）", "type": 0, "settingInfo": {"allowTeamSignUp": true, "isProblemAutoOpen": false, "needSignUpField": false, "rankFrozenMillisecond": 3600000, "excitationStatus": "Finished", "problemOriginal": true, "needRankFrozen": true, "rankFrozenMinute": 60, "logoUrl": "https://uploadfiles.nowcoder.com/images/20230504/276967795_1683173957567/3BB778ABCD26602182C8F4B350BEEF9E", "needSignUpRedirect": false, "forceOnlyMyStatusFilter": true, "needUserNameFormat": false, "organizerSchool": "西南科技大学", "sameEndTimeAsSignUpEnd": true, "managerList": [557767686], "needPassword": false, "organizerName": "西南科技大学", "needCharge": false, "allowMessage": true, "ratingStatus": "No", "needRatingUpperLimit": false, "rankSaveStatus": "Finished"}, "countDownTime": -1539559412, "signUpCount": 306, "contestId": 57322, "contestSignUpEndTime": 1683453600000, "userLevel": 1, "teamId": 0, "isManager": false, "isTeamSignUp": false, "contestSignUpStartTime": 1683172800000, "signUpCountDownTime": -1802359412, "filledPassword": false, "start_time": 1683435600, "end_time": 1683453600, "durationSeconds": 18000, "name": "第十九届西南科技大学ACM程序设计竞赛（同步赛）", "platform": "牛客", "contest_url": "https://ac.nowcoder.com/acm/contest/57322"},{"isSignUp": false, "teamName": "", "contestDuration": 18000000, "contestEndTime": 1683451800000, "contestStartTime": 1683433800000, "topCategoryId": 14, "creatorId": 807217677, "creatorName": "Karashi", "signUpEndCountDownTime": -1523359413, "contestName": "北华大学第九届程序设计竞赛（同步赛）", "type": 0, "settingInfo": {"allowTeamSignUp": true, "isProblemAutoOpen": false, "needSignUpField": false, "excitationStatus": "Finished", "problemOriginal": true, "needRankFrozen": false, "logoUrl": "https://uploadfiles.nowcoder.com/images/20230430/807217677_1682854852079/CC1FBB9884D1A2BFA5808DA70272B018", "needSignUpRedirect": false, "forceOnlyMyStatusFilter": false, "needUserNameFormat": false, "organizerSchool": "北华大学", "sameEndTimeAsSignUpEnd": true, "managerList": [], "needPassword": false, "organizerName": "nowcoder", "needCharge": false, "allowMessage": true, "ratingStatus": "No", "needRatingUpperLimit": false, "rankSaveStatus": "Finished"}, "countDownTime": -1541359413, "signUpCount": 823, "contestId": 57071, "contestSignUpEndTime": 1683451800000, "userLevel": 5, "teamId": 0, "isManager": false, "isTeamSignUp": false, "contestSignUpStartTime": 1682834400000, "signUpCountDownTime": -2140759413, "filledPassword": false, "start_time": 1683433800, "end_time": 1683451800, "durationSeconds": 18000, "name": "北华大学第九届程序设计竞赛（同步赛）", "platform": "牛客", "contest_url": "https://ac.nowcoder.com/acm/contest/57071"},{"isSignUp": false, "teamName": "", "contestDuration": 18000000, "contestEndTime": 1683021600000, "contestStartTime": 1683003600000, "topCategoryId": 14, "creatorId": 771346787, "creatorName": "TYUT_20_李沛霖", "signUpEndCountDownTime": -1953559415, "contestName": "第五届太原理工大学程序设计新生赛决赛（重现赛）", "type": 0, "settingInfo": {"allowTeamSignUp": false, "isProblemAutoOpen": false, "needSignUpField": false, "rankFrozenMillisecond": 3600000, "excitationStatus": "Finished", "problemOriginal": true, "needRankFrozen": true, "rankFrozenMinute": 60, "logoUrl": "https://uploadfiles.nowcoder.com/images/20230421/999991351_1682057204220/C8996E4D3E25AFABA3BFA5B6331C2A88", "needSignUpRedirect": false, "forceOnlyMyStatusFilter": true, "needUserNameFormat": false, "organizerSchool": "太原理工大学", "sameEndTimeAsSignUpEnd": true, "managerList": [], "needPassword": false, "organizerName": "太原理工大学", "needCharge": false, "allowMessage": true, "ratingStatus": "No", "needRatingUpperLimit": false, "rankSaveStatus": "Finished"}, "countDownTime": -1971559415, "signUpCount": 448, "contestId": 56446, "contestSignUpEndTime": 1683021600000, "userLevel": 3, "teamId": 0, "isManager": false, "isTeamSignUp": false, "contestSignUpStartTime": 1682007461000, "signUpCountDownTime": -2967698415, "filledPassword": false, "start_time": 1683003600, "end_time": 1683021600, "durationSeconds": 18000, "name": "第五届太原理工大学程序设计新生赛决赛（重现赛）", "platform": "牛客", "contest_url": "https://ac.nowcoder.com/acm/contest/56446"},{"isSignUp": false, "teamName": "", "contestDuration": 18000000, "contestEndTime": 1681641000000, "contestStartTime": 1681623000000, "topCategoryId": 14, "creatorId": 241178693, "creatorName": "Prgl", "signUpEndCountDownTime": -3334159416, "contestName": "2023年安徽大学第十五届程序设计竞赛（同步赛）", "type": 0, "settingInfo": {"allowTeamSignUp": false, "isProblemAutoOpen": false, "needSignUpField": false, "rankFrozenMillisecond": 3600000, "excitationStatus": "Finished", "problemOriginal": true, "needRankFrozen": true, "rankFrozenMinute": 60, "logoUrl": "https://uploadfiles.nowcoder.com/images/20230406/241178693_1680754148998/D18B15D8696534F84A6170F5FE697A1E", "needSignUpRedirect": false, "forceOnlyMyStatusFilter": true, "needUserNameFormat": false, "organizerSchool": "安徽大学", "sameEndTimeAsSignUpEnd": true, "managerList": [500266860, 109460561], "needPassword": false, "organizerName": "安徽大学", "needCharge": false, "allowMessage": true, "ratingStatus": "No", "needRatingUpperLimit": false, "rankSaveStatus": "Finished"}, "countDownTime": -3352159416, "signUpCount": 543, "contestId": 55380, "contestSignUpEndTime": 1681641000000, "userLevel": 1, "teamId": 0, "isManager": false, "isTeamSignUp": false, "contestSignUpStartTime": 1680753600000, "signUpCountDownTime": -4221559416, "filledPassword": false, "start_time": 1681623000, "end_time": 1681641000, "durationSeconds": 18000, "name": "2023年安徽大学第十五届程序设计竞赛（同步赛）", "platform": "牛客", "contest_url": "https://ac.nowcoder.com/acm/contest/55380"},{"isSignUp": false, "teamName": "", "contestDuration": 18000000, "contestEndTime": 1681635600000, "contestStartTime": 1681617600000, "topCategoryId": 14, "creatorId": 264258389, "creatorName": "Hushnow_", "signUpEndCountDownTime": -3339559418, "contestName": "第五届SCPC中南民族大学程序设计竞赛（同步赛）", "type": 0, "settingInfo": {"allowTeamSignUp": false, "isProblemAutoOpen": false, "needSignUpField": false, "rankFrozenMillisecond": 3600000, "excitationStatus": "Finished", "problemOriginal": true, "needRankFrozen": true, "rankFrozenMinute": 60, "logoUrl": "https://uploadfiles.nowcoder.com/images/20230410/264258389_1681102389856/C8D4AF69D064FE2220156B3AE828208D", "needSignUpRedirect": false, "forceOnlyMyStatusFilter": true, "needUserNameFormat": false, "organizerSchool": "中南民族大学", "sameEndTimeAsSignUpEnd": true, "managerList": [], "needPassword": false, "organizerName": "nowcoder", "needCharge": false, "allowMessage": true, "ratingStatus": "No", "needRatingUpperLimit": false, "rankSaveStatus": "Finished"}, "countDownTime": -3357559418, "signUpCount": 293, "contestId": 55672, "contestSignUpEndTime": 1681635600000, "userLevel": 5, "teamId": 0, "isManager": false, "isTeamSignUp": false, "contestSignUpStartTime": 1681101372000, "signUpCountDownTime": -3873787418, "filledPassword": false, "start_time": 1681617600, "end_time": 1681635600, "durationSeconds": 18000, "name": "第五届SCPC中南民族大学程序设计竞赛（同步赛）", "platform": "牛客", "contest_url": "https://ac.nowcoder.com/acm/contest/55672"},{"isSignUp": false, "teamName": "", "contestDuration": 14400000, "contestEndTime": 1681633800000, "contestStartTime": 1681619400000, "topCategoryId": 14, "creatorId": 859908207, "creatorName": "tarjen", "signUpEndCountDownTime": -3341359419, "contestName": "上海大学第21届程序设计联赛（春季赛）", "type": 0, "settingInfo": {"allowTeamSignUp": false, "isProblemAutoOpen": false, "needSignUpField": false, "rankFrozenMillisecond": 3600000, "excitationStatus": "Finished", "problemOriginal": true, "needRankFrozen": true, "rankFrozenMinute": 60, "logoUrl": "https://uploadfiles.nowcoder.com/images/20230407/859908207_1680836210573/A583A0113690A708B15FA101CC9832C8", "needSignUpRedirect": false, "forceOnlyMyStatusFilter": true, "needUserNameFormat": false, "organizerSchool": "上海大学", "sameEndTimeAsSignUpEnd": true, "managerList": [2739054], "needPassword": false, "organizerName": "nowcoder", "needCharge": false, "allowMessage": true, "ratingStatus": "No", "needRatingUpperLimit": false, "rankSaveStatus": "Finished"}, "countDownTime": -3355759419, "signUpCount": 254, "contestId": 55478, "contestSignUpEndTime": 1681633800000, "userLevel": 4, "teamId": 0, "isManager": false, "isTeamSignUp": false, "contestSignUpStartTime": 1680760800000, "signUpCountDownTime": -4214359419, "filledPassword": false, "start_time": 1681619400, "end_time": 1681633800, "durationSeconds": 14400, "name": "上海大学第21届程序设计联赛（春季赛）", "platform": "牛客", "contest_url": "https://ac.nowcoder.com/acm/contest/55478"},{"isSignUp": false, "teamName": "", "contestDuration": 18000000, "contestEndTime": 1681549200000, "contestStartTime": 1681531200000, "topCategoryId": 14, "creatorId": 771346787, "creatorName": "TYUT_20_李沛霖", "signUpEndCountDownTime": -3425959421, "contestName": "第五届太原理工大学程序设计竞赛新生赛（同步赛）", "type": 0, "settingInfo": {"allowTeamSignUp": false, "isProblemAutoOpen": false, "needSignUpField": false, "rankFrozenMillisecond": 3600000, "excitationStatus": "Finished", "problemOriginal": true, "needRankFrozen": true, "rankFrozenMinute": 60, "logoUrl": "https://uploadfiles.nowcoder.com/images/20230410/999991351_1681108281263/C8996E4D3E25AFABA3BFA5B6331C2A88", "needSignUpRedirect": false, "forceOnlyMyStatusFilter": true, "needUserNameFormat": false, "organizerSchool": "太原理工大学", "sameEndTimeAsSignUpEnd": true, "managerList": [796329161, 837567006, 389760817, 209758447, 200510059], "needPassword": false, "organizerName": "太原理工大学", "needCharge": false, "allowMessage": true, "ratingStatus": "No", "needRatingUpperLimit": false, "rankSaveStatus": "Finished"}, "countDownTime": -3443959421, "signUpCount": 661, "contestId": 55352, "contestSignUpEndTime": 1681549200000, "userLevel": 3, "teamId": 0, "isManager": false, "isTeamSignUp": false, "contestSignUpStartTime": 1680674400000, "signUpCountDownTime": -4300759421, "filledPassword": false, "start_time": 1681531200, "end_time": 1681549200, "durationSeconds": 18000, "name": "第五届太原理工大学程序设计竞赛新生赛（同步赛）", "platform": "牛客", "contest_url": "https://ac.nowcoder.com/acm/contest/55352"}]