[{"isSignUp": false, "teamName": "", "contestDuration": 1386000000, "contestEndTime": 1658044800000, "contestStartTime": 1656658800000, "topCategoryId": 13, "creatorId": 554662, "creatorName": "荷塘涟漪", "signUpEndCountDownTime": 1079531823, "contestName": "2022图论班第三章网络流例题与习题", "type": 0, "settingInfo": {"allowTeamSignUp": false, "isProblemAutoOpen": false, "needSignUpField": false, "problemOriginal": false, "needRankFrozen": false, "needSignUpRedirect": false, "forceOnlyMyStatusFilter": false, "logoUrl": "https://uploadfiles.nowcoder.com/images/20220701/554662_1656656503598/468D5CF649C29CFEFC31A56DEEF0662D", "needUserNameFormat": false, "organizerSchool": "", "sameEndTimeAsSignUpEnd": true, "managerList": [], "needPassword": false, "organizerName": "牛客", "needCharge": false, "allowMessage": false, "ratingStatus": "No", "needRatingUpperLimit": false, "rankSaveStatus": "No"}, "countDownTime": -306468177, "signUpCount": 129, "contestId": 36913, "contestSignUpEndTime": 1658044800000, "userLevel": 7, "teamId": 0, "isManager": false, "isTeamSignUp": false, "contestSignUpStartTime": 1656656700000, "signUpCountDownTime": -308568177, "filledPassword": false, "start_time": 1656658800, "end_time": 1658044800, "durationSeconds": 1386000, "name": "2022图论班第三章网络流例题与习题", "platform": "牛客", "contest_url": "https://ac.nowcoder.com/acm/contest/36913"},{"isSignUp": false, "teamName": "", "contestDuration": 7200000, "contestEndTime": 1657285200000, "contestStartTime": 1657278000000, "topCategoryId": 13, "creatorId": 999991351, "creatorName": "王清楚", "signUpEndCountDownTime": 319931821, "contestName": "牛客小白月赛53", "type": 0, "settingInfo": {"allowTeamSignUp": false, "isProblemAutoOpen": true, "needSignUpField": false, "problemOriginal": true, "needRankFrozen": false, "logoUrl": "https://uploadfiles.nowcoder.com/images/20220628/999991351_1656405652756/732108E8190586D3D0B21C23737FCE04", "needSignUpRedirect": false, "forceOnlyMyStatusFilter": false, "needUserNameFormat": false, "sameEndTimeAsSignUpEnd": true, "ratingUpperLimit": 1499, "needPassword": false, "organizerName": "nowcoder.com", "needCharge": false, "allowMessage": true, "ratingStatus": "Waiting", "needRatingUpperLimit": true, "rankSaveStatus": "No"}, "countDownTime": 312731821, "signUpCount": 622, "contestId": 11230, "contestSignUpEndTime": 1657285200000, "userLevel": 8, "teamId": 0, "isManager": false, "isTeamSignUp": false, "contestSignUpStartTime": 1656381600000, "signUpCountDownTime": -583668179, "filledPassword": false, "start_time": 1657278000, "end_time": 1657285200, "durationSeconds": 7200, "name": "牛客小白月赛53", "platform": "牛客", "contest_url": "https://ac.nowcoder.com/acm/contest/11230"},{"isSignUp": false, "teamName": "", "contestDuration": 10800000, "contestEndTime": 1657893600000, "contestStartTime": 1657882800000, "topCategoryId": 13, "creatorId": 999991351, "creatorName": "王清楚", "signUpEndCountDownTime": 928331820, "contestName": "牛客挑战赛62", "type": 0, "settingInfo": {"allowTeamSignUp": false, "isProblemAutoOpen": true, "needSignUpField": false, "problemOriginal": true, "needRankFrozen": false, "logoUrl": "https://uploadfiles.nowcoder.com/images/20220628/999991351_1656406259945/B6D95C90C20C37C1F467623E0D80F1FA", "needSignUpRedirect": false, "forceOnlyMyStatusFilter": false, "needUserNameFormat": false, "sameEndTimeAsSignUpEnd": true, "needPassword": false, "organizerName": "nowcoder.com", "needCharge": false, "allowMessage": true, "ratingStatus": "Waiting", "needRatingUpperLimit": false, "rankSaveStatus": "No"}, "countDownTime": 917531820, "signUpCount": 263, "contestId": 11202, "contestSignUpEndTime": 1657893600000, "userLevel": 8, "teamId": 0, "isManager": false, "isTeamSignUp": false, "contestSignUpStartTime": 1656381600000, "signUpCountDownTime": -583668180, "filledPassword": false, "start_time": 1657882800, "end_time": 1657893600, "durationSeconds": 10800, "name": "牛客挑战赛62", "platform": "牛客", "contest_url": "https://ac.nowcoder.com/acm/contest/11202"},{"isSignUp": false, "teamName": "", "contestDuration": 18000000, "contestEndTime": 1658134800000, "contestStartTime": 1658116800000, "topCategoryId": 13, "creatorId": 999991351, "creatorName": "王清楚", "signUpEndCountDownTime": 1169531818, "contestName": "\"蔚来杯\"2022牛客暑期多校训练营1", "type": 0, "settingInfo": {"allowTeamSignUp": true, "isProblemAutoOpen": false, "needSignUpField": false, "signUpUrl": "https://competition.nowcoder.com/1/introduce", "rankFrozenMillisecond": 3600000, "problemOriginal": true, "needRankFrozen": true, "rankFrozenMinute": 60, "logoUrl": "https://uploadfiles.nowcoder.com/images/20220513/999991351_1652438727070/BE9E00E9E6724A22F681BA949983485B", "needSignUpRedirect": true, "forceOnlyMyStatusFilter": true, "needUserNameFormat": false, "purchaseUrl": "https://competition.nowcoder.com/1/introduce", "sameEndTimeAsSignUpEnd": true, "needPassword": false, "organizerName": "nowcoder.com", "needCharge": true, "allowMessage": true, "ratingStatus": "Waiting", "needRatingUpperLimit": false, "rankSaveStatus": "No"}, "countDownTime": 1151531818, "signUpCount": 2901, "contestId": 33186, "contestSignUpEndTime": 1658134800000, "userLevel": 8, "teamId": 0, "isManager": false, "isTeamSignUp": false, "contestSignUpStartTime": 1650247200000, "signUpCountDownTime": -6718068182, "filledPassword": false, "start_time": 1658116800, "end_time": 1658134800, "durationSeconds": 18000, "name": "\"蔚来杯\"2022牛客暑期多校训练营1", "platform": "牛客", "contest_url": "https://ac.nowcoder.com/acm/contest/33186"},{"isSignUp": false, "teamName": "", "contestDuration": 18000000, "contestEndTime": 1658566800000, "contestStartTime": 1658548800000, "topCategoryId": 13, "creatorId": 999991351, "creatorName": "王清楚", "signUpEndCountDownTime": 1601531817, "contestName": "\"蔚来杯\"2022牛客暑期多校训练营2", "type": 0, "settingInfo": {"allowTeamSignUp": true, "isProblemAutoOpen": false, "needSignUpField": false, "signUpUrl": "https://competition.nowcoder.com/1/introduce", "rankFrozenMillisecond": 3600000, "problemOriginal": true, "needRankFrozen": true, "rankFrozenMinute": 60, "logoUrl": "https://uploadfiles.nowcoder.com/images/20220516/999991351_1652670813319/BE9E00E9E6724A22F681BA949983485B", "needSignUpRedirect": true, "forceOnlyMyStatusFilter": true, "needUserNameFormat": false, "purchaseUrl": "https://competition.nowcoder.com/1/introduce", "sameEndTimeAsSignUpEnd": true, "needPassword": false, "organizerName": "nowcoder.com", "needCharge": true, "allowMessage": true, "ratingStatus": "Waiting", "needRatingUpperLimit": false, "rankSaveStatus": "No"}, "countDownTime": 1583531817, "signUpCount": 2894, "contestId": 33187, "contestSignUpEndTime": 1658566800000, "userLevel": 8, "teamId": 0, "isManager": false, "isTeamSignUp": false, "contestSignUpStartTime": 1650247200000, "signUpCountDownTime": -6718068183, "filledPassword": false, "start_time": 1658548800, "end_time": 1658566800, "durationSeconds": 18000, "name": "\"蔚来杯\"2022牛客暑期多校训练营2", "platform": "牛客", "contest_url": "https://ac.nowcoder.com/acm/contest/33187"},{"isSignUp": false, "teamName": "", "contestDuration": 18000000, "contestEndTime": 1658739600000, "contestStartTime": 1658721600000, "topCategoryId": 13, "creatorId": 999991351, "creatorName": "王清楚", "signUpEndCountDownTime": 1774331815, "contestName": "\"蔚来杯\"2022牛客暑期多校训练营3", "type": 0, "settingInfo": {"allowTeamSignUp": true, "isProblemAutoOpen": false, "needSignUpField": false, "rankFrozenMillisecond": 3600000, "problemOriginal": true, "needRankFrozen": true, "rankFrozenMinute": 60, "logoUrl": "https://uploadfiles.nowcoder.com/images/20220516/999991351_1652670872118/BE9E00E9E6724A22F681BA949983485B", "needSignUpRedirect": false, "forceOnlyMyStatusFilter": true, "needUserNameFormat": false, "purchaseUrl": "https://ac.nowcoder.com/acm/contest/vip-index", "sameEndTimeAsSignUpEnd": true, "needPassword": false, "organizerName": "nowcoder.com", "needCharge": true, "allowMessage": true, "ratingStatus": "No", "needRatingUpperLimit": false, "rankSaveStatus": "No"}, "countDownTime": 1756331815, "signUpCount": 2894, "contestId": 33188, "contestSignUpEndTime": 1658739600000, "userLevel": 8, "teamId": 0, "isManager": false, "isTeamSignUp": false, "contestSignUpStartTime": 1650247200000, "signUpCountDownTime": -6718068185, "filledPassword": false, "start_time": 1658721600, "end_time": 1658739600, "durationSeconds": 18000, "name": "\"蔚来杯\"2022牛客暑期多校训练营3", "platform": "牛客", "contest_url": "https://ac.nowcoder.com/acm/contest/33188"},{"isSignUp": false, "teamName": "", "contestDuration": 2077200000, "contestEndTime": 1656576000000, "contestStartTime": 1654498800000, "topCategoryId": 13, "creatorId": 999991351, "creatorName": "王清楚", "signUpEndCountDownTime": -389268360, "contestName": "牛客竞赛计算几何专题班扫描线", "type": 0, "settingInfo": {"allowTeamSignUp": false, "isProblemAutoOpen": true, "needSignUpField": false, "excitationStatus": "Finished", "problemOriginal": false, "needRankFrozen": false, "logoUrl": "https://uploadfiles.nowcoder.com/images/20220606/999991351_1654497723633/66D335B1D3A529B4DD3EF6A526814F3B", "needSignUpRedirect": false, "forceOnlyMyStatusFilter": false, "needUserNameFormat": false, "sameEndTimeAsSignUpEnd": true, "managerList": [998122374, 559587208], "needPassword": false, "organizerName": "nowcoder.com", "needCharge": false, "allowMessage": true, "ratingStatus": "No", "needRatingUpperLimit": false, "rankSaveStatus": "Finished"}, "countDownTime": -2466468360, "signUpCount": 351, "contestId": 36088, "contestSignUpEndTime": 1656576000000, "userLevel": 8, "teamId": 0, "isManager": false, "isTeamSignUp": false, "contestSignUpStartTime": 1654480800000, "signUpCountDownTime": -2484468360, "filledPassword": false, "start_time": 1654498800, "end_time": 1656576000, "durationSeconds": 2077200, "name": "牛客竞赛计算几何专题班扫描线", "platform": "牛客", "contest_url": "https://ac.nowcoder.com/acm/contest/36088"},{"isSignUp": false, "teamName": "", "contestDuration": 9000000, "contestEndTime": 1656077400000, "contestStartTime": 1656068400000, "topCategoryId": 13, "creatorId": 999991351, "creatorName": "王清楚", "signUpEndCountDownTime": -887868362, "contestName": "牛客练习赛101", "type": 0, "settingInfo": {"allowTeamSignUp": false, "isProblemAutoOpen": true, "needSignUpField": false, "excitationStatus": "Finished", "problemOriginal": true, "needRankFrozen": false, "logoUrl": "https://uploadfiles.nowcoder.com/images/20220617/999991351_1655437496614/4A338599A4C130236C8E9E700B89A7B2", "needSignUpRedirect": false, "forceOnlyMyStatusFilter": false, "needUserNameFormat": false, "sameEndTimeAsSignUpEnd": true, "ratingUpperLimit": 2199, "managerList": [675586547, 9955525, 1101920], "needPassword": false, "organizerName": "nowcoder.com", "needCharge": false, "allowMessage": true, "ratingStatus": "Finished", "needRatingUpperLimit": true, "rankSaveStatus": "No"}, "countDownTime": -896868362, "signUpCount": 1053, "contestId": 11247, "contestSignUpEndTime": 1656077400000, "userLevel": 8, "teamId": 0, "isManager": false, "isTeamSignUp": false, "contestSignUpStartTime": 1655431200000, "signUpCountDownTime": -1534068362, "filledPassword": false, "start_time": 1656068400, "end_time": 1656077400, "durationSeconds": 9000, "name": "牛客练习赛101", "platform": "牛客", "contest_url": "https://ac.nowcoder.com/acm/contest/11247"},{"isSignUp": false, "teamName": "", "contestDuration": 7200000, "contestEndTime": 1655557200000, "contestStartTime": 1655550000000, "topCategoryId": 13, "creatorId": 999991351, "creatorName": "王清楚", "signUpEndCountDownTime": -1408068364, "contestName": "牛客小白月赛52", "type": 0, "settingInfo": {"allowTeamSignUp": false, "isProblemAutoOpen": true, "needSignUpField": false, "excitationStatus": "Finished", "problemOriginal": true, "needRankFrozen": false, "logoUrl": "https://uploadfiles.nowcoder.com/images/20220613/999991351_1655110761117/732108E8190586D3D0B21C23737FCE04", "needSignUpRedirect": false, "forceOnlyMyStatusFilter": false, "needUserNameFormat": false, "sameEndTimeAsSignUpEnd": true, "ratingUpperLimit": 1499, "managerList": [432715231, 177389685, 718025342, 839549920, 567730185, 839549920], "needPassword": false, "organizerName": "nowcoder.com", "needCharge": false, "allowMessage": true, "ratingStatus": "Finished", "needRatingUpperLimit": true, "rankSaveStatus": "No"}, "countDownTime": -1415268364, "signUpCount": 786, "contestId": 11229, "contestSignUpEndTime": 1655557200000, "userLevel": 8, "teamId": 0, "isManager": false, "isTeamSignUp": false, "contestSignUpStartTime": 1655085600000, "signUpCountDownTime": -1879668364, "filledPassword": false, "start_time": 1655550000, "end_time": 1655557200, "durationSeconds": 7200, "name": "牛客小白月赛52", "platform": "牛客", "contest_url": "https://ac.nowcoder.com/acm/contest/11229"},{"isSignUp": false, "teamName": "", "contestDuration": 10800000, "contestEndTime": 1655474400000, "contestStartTime": 1655463600000, "topCategoryId": 13, "creatorId": 999991351, "creatorName": "王清楚", "signUpEndCountDownTime": -1490868366, "contestName": "牛客挑战赛61", "type": 0, "settingInfo": {"allowTeamSignUp": false, "isProblemAutoOpen": true, "needSignUpField": false, "excitationStatus": "Finished", "problemOriginal": true, "needRankFrozen": false, "logoUrl": "https://uploadfiles.nowcoder.com/images/20220606/999991351_1654483939393/B6D95C90C20C37C1F467623E0D80F1FA", "needSignUpRedirect": false, "forceOnlyMyStatusFilter": false, "needUserNameFormat": false, "sameEndTimeAsSignUpEnd": true, "managerList": [559587208, 450550838, 842052928, 932882676], "needPassword": false, "organizerName": "nowcoder.com", "needCharge": false, "allowMessage": true, "ratingStatus": "Finished", "needRatingUpperLimit": false, "rankSaveStatus": "No"}, "countDownTime": -1501668366, "signUpCount": 716, "contestId": 11201, "contestSignUpEndTime": 1655474400000, "userLevel": 8, "teamId": 0, "isManager": false, "isTeamSignUp": false, "contestSignUpStartTime": 1654480800000, "signUpCountDownTime": -2484468366, "filledPassword": false, "start_time": 1655463600, "end_time": 1655474400, "durationSeconds": 10800, "name": "牛客挑战赛61", "platform": "牛客", "contest_url": "https://ac.nowcoder.com/acm/contest/11201"},{"isSignUp": false, "teamName": "", "contestDuration": 9000000, "contestEndTime": 1654867800000, "contestStartTime": 1654858800000, "topCategoryId": 13, "creatorId": 999991351, "creatorName": "王清楚", "signUpEndCountDownTime": -2097468367, "contestName": "牛客练习赛100", "type": 0, "settingInfo": {"allowTeamSignUp": false, "isProblemAutoOpen": true, "needSignUpField": false, "excitationStatus": "Finished", "problemOriginal": true, "needRankFrozen": false, "logoUrl": "https://uploadfiles.nowcoder.com/images/20220530/999991351_1653893235867/4A338599A4C130236C8E9E700B89A7B2", "needSignUpRedirect": false, "forceOnlyMyStatusFilter": false, "needUserNameFormat": false, "sameEndTimeAsSignUpEnd": true, "ratingUpperLimit": 2199, "managerList": [236063124, 9955525, 1101920, 8582211, 919247], "needPassword": false, "organizerName": "nowcoder.com", "needCharge": false, "allowMessage": true, "ratingStatus": "Finished", "needRatingUpperLimit": true, "rankSaveStatus": "No"}, "countDownTime": -2106468367, "signUpCount": 1013, "contestId": 11251, "contestSignUpEndTime": 1654867800000, "userLevel": 8, "teamId": 0, "isManager": false, "isTeamSignUp": false, "contestSignUpStartTime": 1653876000000, "signUpCountDownTime": -3089268367, "filledPassword": false, "start_time": 1654858800, "end_time": 1654867800, "durationSeconds": 9000, "name": "牛客练习赛100", "platform": "牛客", "contest_url": "https://ac.nowcoder.com/acm/contest/11251"},{"isSignUp": false, "teamName": "", "contestDuration": 790200000, "contestEndTime": 1654761600000, "contestStartTime": 1653971400000, "topCategoryId": 13, "creatorId": 554662, "creatorName": "荷塘涟漪", "signUpEndCountDownTime": -2203668369, "contestName": "2022图论班第二章连通性例题与习题", "type": 0, "settingInfo": {"allowTeamSignUp": false, "isProblemAutoOpen": false, "needSignUpField": false, "excitationStatus": "Finished", "problemOriginal": false, "needRankFrozen": false, "needSignUpRedirect": false, "forceOnlyMyStatusFilter": false, "logoUrl": "https://uploadfiles.nowcoder.com/images/20220531/554662_1653969629756/468D5CF649C29CFEFC31A56DEEF0662D", "needUserNameFormat": false, "organizerSchool": "", "sameEndTimeAsSignUpEnd": true, "managerList": [], "needPassword": false, "organizerName": "牛客", "needCharge": false, "allowMessage": false, "ratingStatus": "No", "needRatingUpperLimit": false, "rankSaveStatus": "Finished"}, "countDownTime": -2993868369, "signUpCount": 205, "contestId": 35796, "contestSignUpEndTime": 1654761600000, "userLevel": 7, "teamId": 0, "isManager": false, "isTeamSignUp": false, "contestSignUpStartTime": 1653971400000, "signUpCountDownTime": -2993868369, "filledPassword": false, "start_time": 1653971400, "end_time": 1654761600, "durationSeconds": 790200, "name": "2022图论班第二章连通性例题与习题", "platform": "牛客", "contest_url": "https://ac.nowcoder.com/acm/contest/35796"},{"isSignUp": false, "teamName": "", "contestDuration": 7200000, "contestEndTime": 1654261200000, "contestStartTime": 1654254000000, "topCategoryId": 13, "creatorId": 999991351, "creatorName": "王清楚", "signUpEndCountDownTime": -2704068370, "contestName": "牛客小白月赛51", "type": 0, "settingInfo": {"allowTeamSignUp": false, "isProblemAutoOpen": true, "needSignUpField": false, "excitationStatus": "Finished", "problemOriginal": true, "needRankFrozen": false, "logoUrl": "https://uploadfiles.nowcoder.com/images/20220527/999991351_1653650740258/732108E8190586D3D0B21C23737FCE04", "needSignUpRedirect": false, "forceOnlyMyStatusFilter": false, "needUserNameFormat": false, "sameEndTimeAsSignUpEnd": true, "ratingUpperLimit": 1499, "managerList": [236063124, 567730185, 718025342, 177389685], "needPassword": false, "organizerName": "nowcoder.com", "needCharge": false, "allowMessage": true, "ratingStatus": "Finished", "needRatingUpperLimit": true, "rankSaveStatus": "No"}, "countDownTime": -2711268370, "signUpCount": 1220, "contestId": 11228, "contestSignUpEndTime": 1654261200000, "userLevel": 8, "teamId": 0, "isManager": false, "isTeamSignUp": false, "contestSignUpStartTime": 1653616800000, "signUpCountDownTime": -3348468370, "filledPassword": false, "start_time": 1654254000, "end_time": 1654261200, "durationSeconds": 7200, "name": "牛客小白月赛51", "platform": "牛客", "contest_url": "https://ac.nowcoder.com/acm/contest/11228"},{"isSignUp": false, "teamName": "", "contestDuration": 7200000, "contestEndTime": 1654088400000, "contestStartTime": 1654081200000, "topCategoryId": 13, "creatorId": 999991351, "creatorName": "王清楚", "signUpEndCountDownTime": -2876868372, "contestName": "牛客2022年儿童节比赛", "type": 0, "settingInfo": {"allowTeamSignUp": false, "isProblemAutoOpen": true, "needSignUpField": false, "rankFrozenMillisecond": 1200000, "excitationStatus": "Finished", "problemOriginal": true, "needRankFrozen": true, "rankFrozenMinute": 20, "logoUrl": "https://uploadfiles.nowcoder.com/images/20220522/999991351_1653194608430/E5CAE5FD8E655AC7D1703A03A64E2858", "needSignUpRedirect": false, "forceOnlyMyStatusFilter": true, "needUserNameFormat": false, "sameEndTimeAsSignUpEnd": true, "managerList": [236063124, 7924887, 540562653, 150439955, 5326482, 332653690], "needPassword": false, "organizerName": "nowcoder.com", "needCharge": false, "allowMessage": true, "ratingStatus": "No", "needRatingUpperLimit": false, "rankSaveStatus": "Finished"}, "countDownTime": -2884068372, "signUpCount": 1365, "contestId": 35358, "contestSignUpEndTime": 1654088400000, "userLevel": 8, "teamId": 0, "isManager": false, "isTeamSignUp": false, "contestSignUpStartTime": 1653184800000, "signUpCountDownTime": -3780468372, "filledPassword": false, "start_time": 1654081200, "end_time": 1654088400, "durationSeconds": 7200, "name": "牛客2022年儿童节比赛", "platform": "牛客", "contest_url": "https://ac.nowcoder.com/acm/contest/35358"},{"isSignUp": false, "teamName": "", "contestDuration": 1476000000, "contestEndTime": 1653897600000, "contestStartTime": 1652421600000, "topCategoryId": 13, "creatorId": 554662, "creatorName": "荷塘涟漪", "signUpEndCountDownTime": -3067668374, "contestName": "2022图论班第一章图匹配例题与习题", "type": 0, "settingInfo": {"allowTeamSignUp": false, "isProblemAutoOpen": false, "needSignUpField": false, "excitationStatus": "Finished", "problemOriginal": false, "needRankFrozen": false, "needSignUpRedirect": false, "forceOnlyMyStatusFilter": false, "logoUrl": "https://uploadfiles.nowcoder.com/images/20220513/554662_1652416763163/468D5CF649C29CFEFC31A56DEEF0662D", "needUserNameFormat": false, "organizerSchool": "", "sameEndTimeAsSignUpEnd": true, "managerList": [], "needPassword": false, "organizerName": "牛客", "needCharge": false, "allowMessage": false, "ratingStatus": "No", "needRatingUpperLimit": false, "rankSaveStatus": "Finished"}, "countDownTime": -4543668374, "signUpCount": 488, "contestId": 34649, "contestSignUpEndTime": 1653897600000, "userLevel": 7, "teamId": 0, "isManager": false, "isTeamSignUp": false, "contestSignUpStartTime": 1652421600000, "signUpCountDownTime": -4543668374, "filledPassword": false, "start_time": 1652421600, "end_time": 1653897600, "durationSeconds": 1476000, "name": "2022图论班第一章图匹配例题与习题", "platform": "牛客", "contest_url": "https://ac.nowcoder.com/acm/contest/34649"},{"isSignUp": false, "teamName": "", "contestDuration": 18000000, "contestEndTime": 1653732000000, "contestStartTime": 1653714000000, "topCategoryId": 13, "creatorId": 999991351, "creatorName": "王清楚", "signUpEndCountDownTime": -3949668375, "contestName": "2021年ICPC国际大学生程序设计竞赛暨陕西省第九届大学生程序设计竞赛（正式赛）", "type": 0, "settingInfo": {"allowTeamSignUp": false, "isProblemAutoOpen": true, "needSignUpField": false, "rankFrozenMillisecond": 3600000, "excitationStatus": "Finished", "problemOriginal": true, "needRankFrozen": true, "rankFrozenMinute": 60, "logoUrl": "https://uploadfiles.nowcoder.com/images/20220520/999991351_1653028062178/461C1592E7EFB8300A385340F02A3BC6", "needSignUpRedirect": false, "forceOnlyMyStatusFilter": true, "needUserNameFormat": false, "sameEndTimeAsSignUpEnd": false, "managerList": [7419365, 4187969, 112634775, 355082930], "needPassword": false, "organizerName": "ICPC", "needCharge": false, "allowMessage": true, "ratingStatus": "No", "needRatingUpperLimit": false, "rankSaveStatus": "Finished"}, "countDownTime": -3251268375, "signUpCount": 106, "contestId": 35232, "contestSignUpEndTime": 1653015600000, "userLevel": 8, "teamId": 0, "isManager": false, "isTeamSignUp": false, "contestSignUpStartTime": 1653012000000, "signUpCountDownTime": -3953268375, "filledPassword": false, "start_time": 1653714000, "end_time": 1653732000, "durationSeconds": 18000, "name": "2021年ICPC国际大学生程序设计竞赛暨陕西省第九届大学生程序设计竞赛（正式赛）", "platform": "牛客", "contest_url": "https://ac.nowcoder.com/acm/contest/35232"}]